dung_pt/__init__.py
dung_pt/telegram/__init__.py
dung_pt/telegram/telegram.py
dung_pt-1.0.dist-info/LICENSE
dung_pt-1.0.dist-info/METADATA
dung_pt-1.0.dist-info/WHEEL
dung_pt-1.0.dist-info/top_level.txt
dung_pt-1.0.dist-info/RECORD
