Metadata-Version: 2.1
Name: dung_pt
Version: 1.0
Summary: thu vien dung_pt
Author: VuDung
Author-email: VuDung <vuhuudung@gmail.com>
Project-URL: Homepage, https://github.com
Classifier: Programming Language :: Python :: 3
Classifier: License :: OSI Approved :: MIT License
Classifier: Operating System :: OS Independent
Requires-Python: >=3.7
License-File: LICENSE
Requires-Dist: requests
Requires-Dist: pandas
Requires-Dist: openpyxl
Requires-Dist: numpy
